README.md
setup.py
scripts/tinder-token
scripts/tinder-token.py
tinder_token/__init__.py
tinder_token/facebook.py
tinder_token/phone.py
tinder_token.egg-info/PKG-INFO
tinder_token.egg-info/SOURCES.txt
tinder_token.egg-info/dependency_links.txt
tinder_token.egg-info/requires.txt
tinder_token.egg-info/top_level.txt