Metadata-Version: 2.1
Name: tinder-token
Version: 1.0.1
Summary: Python library for generating access tokens for using Tinder API, using Facebook or Phone authentication
Home-page: https://github.com/meister245/tinder-token
Author: Zsolt Mester
Author-email: 
License: MIT
Project-URL: Code, https://github.com/meister245/tinder-token
Project-URL: Issue tracker, https://github.com/meister245/tinder-token/issues
Platform: UNKNOWN
Provides-Extra: facebook
